15-dflipflop/dflipflop.v
/* 
  D-Flip-Flop
  D - Data input
  CLK - Clock input
  RESET - Active-high reset input (asynchronous)
  EN - Enable input
  Q - Output

  Behavior:
  - On the rising edge of CLK:
    - If reset is high, Q is cleared to 0.
    - Else if enable is high, Q follows D.
    - Else, Q retains its value.
*/

module dflipflop (
  input wire d,        // D data input
  input wire clk,      // Clock input
  input wire en,       // Enable input
  input wire reset,    // Asynchronous reset input (active-high)
  output reg q         // Q output
);

  // Asynchronous reset with clocked behavior
  always @ (posedge clk or posedge reset) begin
    if (reset)
      q <= 1'b0;
    else if (en)
      q <= d;
  end

endmodule

15-dflipflop/tb.v
`timescale 1ns/1ps
`include "dflipflop.v"

module tb();

  reg d;
  reg clk;
  reg en;
  reg reset;
  wire q;

  // Instantiate the D flip-flop module
  dflipflop uut (
    .d(d),
    .clk(clk),
    .en(en),
    .reset(reset),
    .q(q)
  );

  // Dump waveform data (for GTKWave)
  initial begin
    $dumpfile("dump.vcd");    // Create VCD file
    $dumpvars(0, tb);         // Dump all variables in the module
  end

  // Clock generation
  initial begin
    clk <= 0;
    forever begin
      #5 clk <= ~clk;         // Toggle clock every 5 ns
    end
  end

  // Stimulus
  initial begin
    en = 1; reset = 0; d = 0;
    #3  d = 1;
    #9  d = 0;
    #6  d = 1;
    #10 d = 0;
    #20 d = 1;
    #23 reset = 1;
    #5  reset = 0;
    #10 en = 0;               // Disable flip-flop
    #3  d = 1;
    #9  d = 0;
    #6  d = 1;
    #23 reset = 1;
    #5  reset = 0;
    #10;
    $finish;
  end

  // Monitor signals
  initial begin
    $monitor("t=%3d, reset=%1b, en=%1b, clk=%1b, d=%1b, q=%1b", 
              $time, reset, en, clk, d, q);
  end

endmodule

15-dflipflop/dump.vcd
$date
	Tue May 20 14:16:53 2025
$end
$version
	Icarus Verilog
$end
$timescale
	1ps
$end
$scope module tb $end
$var wire 1 ! q $end
$var reg 1 " clk $end
$var reg 1 # d $end
$var reg 1 $ en $end
$var reg 1 % reset $end
$scope module uut $end
$var wire 1 " clk $end
$var wire 1 # d $end
$var wire 1 $ en $end
$var wire 1 % reset $end
$var reg 1 ! q $end
$upscope $end
$upscope $end
$enddefinitions $end
#0
$dumpvars
0%
1$
0#
0"
x!
$end
#3000
1#
#5000
1!
1"
#10000
0"
#12000
0#
#15000
0!
1"
#18000
1#
#20000
0"
#25000
1!
1"
#28000
0#
#30000
0"
#35000
0!
1"
#40000
0"
#45000
1"
#48000
1#
#50000
0"
#55000
1!
1"
#60000
0"
#65000
1"
#70000
0"
#71000
0!
1%
#75000
1"
#76000
0%
#80000
0"
#85000
1!
1"
#86000
0$
#90000
0"
#95000
1"
#98000
0#
#100000
0"
#104000
1#
#105000
1"
#110000
0"
#115000
1"
#120000
0"
#125000
1"
#127000
0!
1%
#130000
0"
#132000
0%
