17-fsm/fsm-moore.v
module dividedby3FSM(
    input clk,
    input reset,
    output y
);

    reg [2:0] state, next_state; // Only need 2 bits (00, 01, 10)

    parameter S0 = 2'b00, S1 = 2'b01, S2 = 2'b10;

    // State register
    always @(posedge clk or posedge reset) begin
        if (reset)
            state <= S0;
        else
            state <= next_state;
    end

    // Next state logic
    always @(*) begin
        case (state)
            S0: next_state = S1;
            S1: next_state = S2;
            S2: next_state = S0;
            default: next_state = S0;
        endcase
    end

    // Output logic
    assign y = (state == S0);

endmodule

17-fsm/tb.v
`timescale 1ns/1ps
`include "fsm-moore.v"

module dividedby3FSM_tb;

    reg clk;
    reg reset;
    wire y;

    // Instantiate the DUT (Device Under Test)
    dividedby3FSM uut (
        .clk(clk),
        .reset(reset),
        .y(y)
    );

    // Clock generation
    initial begin
        clk = 0;
        forever #5 clk = ~clk;
    end

    // Stimulus and waveform generation
    initial begin
        $dumpfile("dump.vcd");

        // Dump everything, including internal signals
        $dumpvars(0, dividedby3FSM_tb);

        // Terminal output for reset and y (state not shown in terminal, but will appear in GTKWave)
        $monitor("Time = %0t | reset = %b | y = %b", $time, reset, y);

        // Reset pulse
        reset = 1;
        #10;
        reset = 0;

        #100;
        $finish;
    end

endmodule

17-fsm/dump.vcd
$date
	Tue May 27 15:38:14 2025
$end
$version
	Icarus Verilog
$end
$timescale
	1ps
$end
$scope module dividedby3FSM_tb $end
$var wire 1 ! y $end
$var reg 1 " clk $end
$var reg 1 # reset $end
$scope module uut $end
$var wire 1 " clk $end
$var wire 1 # reset $end
$var wire 1 ! y $end
$var reg 3 $ next_state [2:0] $end
$var reg 3 % state [2:0] $end
$upscope $end
$upscope $end
$enddefinitions $end
#0
$dumpvars
b0 %
b1 $
1#
0"
1!
$end
#5000
1"
#10000
0"
0#
#15000
b10 $
0!
b1 %
1"
#20000
0"
#25000
b0 $
b10 %
1"
#30000
0"
#35000
b1 $
1!
b0 %
1"
#40000
0"
#45000
b10 $
0!
b1 %
1"
#50000
0"
#55000
b0 $
b10 %
1"
#60000
0"
#65000
b1 $
1!
b0 %
1"
#70000
0"
#75000
b10 $
0!
b1 %
1"
#80000
0"
#85000
b0 $
b10 %
1"
#90000
0"
#95000
b1 $
1!
b0 %
1"
#100000
0"
#105000
b10 $
0!
b1 %
1"
