10-FulllAdder/fulladder1b.v
module fulladder1b(
    input wire a,
    input wire b,
    input wire cin,
    output wire s,
    output wire cout
);

assign {cout,s}=a+b+cin;

endmodule

10-FulllAdder/tb.v
`timescale 1ns/1ps
`include "fulladder1b.v"

module tb();
    reg a;
    reg b;
    reg cin;
    wire s;
    wire cout;

    fulladder1b uut (
        .a(a),
        .b(b),
        .cin(cin),
        .s(s),
        .cout(cout)
    );

    initial begin
        $dumpfile("dump.vcd"); // dump file name
        $dumpvars(0, tb); 

        a=1'h0; b=1'h0; cin=1'h0;
        #10 a=1'h0; b=1'h0; cin=1'h1;
        #10 a=1'h0; b=1'h1; cin=1'h0;
        #10 a=1'h0; b=1'h1; cin=1'h1;
        #10 a=1'h1; b=1'h0; cin=1'h0;
        #10 a=1'h1; b=1'h0; cin=1'h1;
        #10 a=1'h1; b=1'h1; cin=1'h0;
        #10 a=1'h1; b=1'h1; cin=1'h1;

        #10 $finish;
    end

    initial begin
        $monitor("a + b + cin = (%b + %b + %b) -> s = %b, cout = %b", a, b, cin, s, cout);
    end
endmodule

10-FulllAdder/dump.vcd
$date
	Tue Apr 29 14:06:06 2025
$end
$version
	Icarus Verilog
$end
$timescale
	1ps
$end
$scope module tb $end
$var wire 1 ! s $end
$var wire 1 " cout $end
$var reg 1 # a $end
$var reg 1 $ b $end
$var reg 1 % cin $end
$scope module uut $end
$var wire 1 # a $end
$var wire 1 $ b $end
$var wire 1 % cin $end
$var wire 1 ! s $end
$var wire 1 " cout $end
$upscope $end
$upscope $end
$enddefinitions $end
#0
$dumpvars
0%
0$
0#
0"
0!
$end
#10000
1!
1%
#20000
0%
1$
#30000
0!
1"
1%
#40000
0"
1!
0%
0$
1#
#50000
0!
1"
1%
#60000
0%
1$
#70000
1!
1%
